{
  "certificado": "certificado",
  "sertificado": "sertificado",
  "cédula": "cédula",
  "cedula": "cedula",
  "sedula": "sedula",
  "permiso": "permiso",
  "patente": "patente",
  "opción uno": "opción uno",
  "opcion uno": "opcion uno",
  "numero uno": "numero uno",
  "número uno": "número uno",
  "opción 1": "opción 1",
  "opcion 1": "opcion 1",
  "numero 1": "numero 1",
  "número 1": "número 1",
  "1": "1",
  "certificado de residencia definitiva": "Certificado de Residencia Definitiva",
  "residencia definitiva": "residencia definitiva",
  "opción dos": "opción dos",
  "opcion dos": "opcion dos",
  "opcion 2": "opcion 2",
  "opción 2": "opción 2",
  "número 2": "número 2",
  "numero 2": "numero 2",
  "número dos": "número dos",
  "numero dos": "numero dos",
  "2": "2",
  "certificado de estadía temporal": "Certificado de Estadía Temporal",
  "estadía temporal": "Estadía Temporal",
  "opción tres": "opción tres",
  "opcion tres": "opcion tres",
  "opcion 3": "opcion 3",
  "opción 3": "opción 3",
  "número 3": "número 3",
  "numero 3": "numero 3",
  "número tres": "número tres",
  "numero tres": "numero tres",
  "3": "3",
  "certificado de extracción productiva": "Certificado de Extracción Productiva",
  "extracción productiva": "Extracción Productiva",
  "opcion cuatro": "opcion cuatro",
  "opción cuatro": "opción cuatro",
  "opcion 4": "opcion 4",
  "opción 4": "opción 4",
  "número 4": "número 4",
  "numero 4": "numero 4",
  "número cuatro": "número cuatro",
  "numero cuatro": "numero cuatro",
  "4": "4",
  "certificado de enrolamiento militar de la república": "Certificado de Enrolamiento Militar de la República",
  "enrolamiento militar": "Enrolamiento Militar",
  "opcion cinco": "opcion cinco",
  "opción cinco": "opción cinco",
  "opcion 5": "opcion 5",
  "opción 5": "opción 5",
  "número 5": "número 5",
  "numero 5": "numero 5",
  "número cinco": "número cinco",
  "numero cinco": "numero cinco",
  "5": "5",
  "certificado registro de carga": "Certificado Registro de Carga",
  "registro de carga": "Registro de Carga",
  "opcion seis": "opcion seis",
  "opción seis": "opción seis",
  "opcion 6": "opcion 6",
  "opción 6": "opción 6",
  "número 6": "número 6",
  "numero 6": "numero 6",
  "número seis": "número seis",
  "numero seis": "numero seis",
  "6": "6",
  "certificado de antecedentes": "Certificado de Antecedentes",
  "antecedentes": "Antecedentes",
  "opcion siete": "opcion siete",
  "opción siete": "opción siete",
  "opcion 7": "opcion 7",
  "opción 7": "opción 7",
  "número 7": "número 7",
  "numero 7": "numero 7",
  "número siete": "número siete",
  "numero siete": "numero siete",
  "7": "7",
  "certificado registro de droides": "Certificado Registro de Droides",
  "registro de droides": "Registro de Droides",
  "opción ocho": "opción ocho",
  "opcion ocho": "opcion ocho",
  "8": "8",
  "numero ocho": "numero ocho",
  "número ocho": "número ocho",
  "numero 8": "numero 8",
  "número 8": "número 8",
  "licencia oficial piloto federado": "Licencia Oficial Piloto Federado",
  "licencia de piloto federado": "Licencia de Piloto Federado",
  "piloto federado": "Piloto Federado",
  "opción nueve": "opción nueve",
  "opcion nueve": "opcion nueve",
  "9": "9",
  "numero nueve": "numero nueve",
  "número nueve": "número nueve",
  "numero 9": "numero 9",
  "número 9": "número 9",
  "licencia de transporte espacial": "Licencia de Transporte Espacial",
  "licencia transporte espacial": "Licencia Transporte Espacial",
  "transporte espacial": "Transporte Espacial",
  "opción diez": "opción diez",
  "opcion diez": "opcion diez",
  "10": "10",
  "numero diez": "numero diez",
  "número diez": "número diez",
  "numero 10": "numero 10",
  "número 10": "número 10",
  "cédula única sistema planetario": "Cédula Única Sistema Planetario",
  "cedula unica sistema planetario": "cedula unica Sistema Planetario",
  "cedula unica": "cedula unica",
  "cédula única": "Cédula Única",
  "opción once": "opción once",
  "opcion once": "opcion once",
  "11": "11",
  "numero once": "numero once",
  "número once": "número once",
  "numero 11": "numero 11",
  "número 11": "número 11",
  "cédula de bienestar social": "Cédula de Bienestar Social",
  "cedula de bienestar": "cedula de Bienestar",
  "bienestar": "Bienestar",
  "opción doce": "opción doce",
  "opcion doce": "opcion doce",
  "12": "12",
  "numero doce": "numero doce",
  "número doce": "número doce",
  "numero 12": "numero 12",
  "número 12": "número 12",
  "permiso de exploración planetaria": "Permiso de Exploración Planetaria",
  "opción trece": "opción trece",
  "opcion trece": "opcion trece",
  "13": "13",
  "numero trece": "numero trece",
  "número trece": "número trece",
  "numero 13": "numero 13",
  "número 13": "número 13",
  "permiso de asentamientos coloniales": "Permiso de Asentamientos Coloniales",
  "asentamientos coloniales": "Asentamientos Coloniales",
  "asentamientos": "asentamientos",
  "opción catorce": "opción catorce",
  "opcion catorce": "opcion catorce",
  "14": "14",
  "numero catorce": "numero catorce",
  "número catorce": "número catorce",
  "numero 14": "numero 14",
  "número 14": "número 14",
  "permiso de aterrizaje": "Permiso de Aterrizaje",
  "aterrizaje": "Aterrizaje",
  "aterrisaje": "Aterrisaje",
  "opción quince": "opción quince",
  "opcion quince": "opcion quince",
  "15": "15",
  "numero quince": "numero quince",
  "número quince": "número quince",
  "numero 15": "numero 15",
  "número 15": "número 15",
  "patente comercial intergálactica": "Patente Comercial Intergálactica",
  "patente comercial intergalactica": "Patente Comercial Intergalactica",
  "patente comercial": "Patente Comercial",
  "comercial": "Comercial",
  "opción dieciseis": "opción dieciseis",
  "opcion dieciseis": "opcion dieciseis",
  "16": "16",
  "numero dieciseis": "numero dieciseis",
  "número dieciseis": "número dieciseis",
  "numero 16": "numero 16",
  "número 16": "número 16",
  "patente de inventos": "Patente de Inventos",
  "requisitos": "requisitos",
  "necesito": "necesito",
  "papeles": "papeles",
  "documentos": "documentos",
  "documentación": "documentación",
  "donde": "donde",
  "a dónde": "a dónde",
  "dónde": "dónde",
  "en donde": "en donde",
  "en dónde": "en dónde",
  "dirección": "dirección",
  "hora": "hora",
  "horario": "horario",
  "correo electrónico": "correo electrónico",
  "correo": "correo",
  "correo electronico": "correo electronico",
  "mail": "mail",
  "e-mail": "e-mail",
  "holocom number": "holocom number",
  "holocom": "holocom",
  "numero": "numero",
  "telefono": "telefono",
  "teléfono": "teléfono",
  "dura": "dura",
  "número": "número",
  "número de telefono": "número de telefono",
  "numero de telefono": "numero de telefono",
  "contacto telefonico": "contacto telefonico",
  "tiempo": "tiempo",
  "validez": "validez",
  "vigencia": "vigencia",
  "tiempo de validez": "tiempo de validez",
  "valides": "valides",
  "multa": "multa",
  "sancion": "sancion",
  "penalidad": "penalidad",
  "sanción": "sanción",
  "penalidades": "penalidades",
  "sanciones": "sanciones",
  "puede pasar": "puede pasar",
  "demostrar": "demostrar",
  "vivo": "vivo",
  "demuestro": "demuestro",
  "acreditar": "acreditar",
  "acredito": "acredito",
  "comprobar": "comprobar",
  "residencia": "residencia",
  "cuidadania": "cuidadania",
  "certificar": "certificar",
  "certifico": "certifico",
  "domicilio": "domicilio",
  "nacionalidad": "nacionalidad",
  "ciudadania": "ciudadania",
  "ciudadanía": "ciudadanía",
  "demuestra": "demuestra",
  "soy": "soy",
  "manejar": "manejar",
  "nave": "nave",
  "pilotar": "pilotar",
  "volar": "volar",
  "conducir": "conducir",
  "caza": "caza",
  "caza estelar": "caza estelar",
  "nave particular": "nave particular",
  "nave espacial": "nave espacial",
  "bombardero": "bombardero",
  "x-wing": "X-wing",
  "millennium falcon": "Millennium Falcon",
  "n-1 starfighter": "N-1 Starfighter",
  "nave de asalto": "nave de asalto",
  "u-wing": "U-wing",
  "patrol transport": "Patrol transport",
  "nave de construcción": "nave de construcción",
  "nave de minería": "nave de minería",
  "nave de transporte": "nave de transporte",
  "nave de comando": "nave de comando",
  "operar": "operar",
  "nave de pasajeros": "nave de pasajeros",
  "nave de rescate": "nave de rescate",
  "destructor": "destructor",
  "carguero": "carguero",
  "transporte": "transporte",
  "transporte de carga": "transporte de carga",
  "transporte de pasajeros": "transporte de pasajeros",
  "nave de carga": "nave de carga",
  "vehículo de carga": "vehículo de carga",
  "transportar": "transportar",
  "mercancias": "mercancias",
  "mercaderias": "mercaderias",
  "bienes": "bienes",
  "renovar": "renovar",
  "carné": "carné",
  "sacar": "sacar",
  "carné de identidad": "carné de identidad",
  "obtener": "obtener",
  "documento de identidad": "documento de identidad",
  "actualizar": "actualizar",
  "documento de identificación": "documento de identificación",
  "cédula de identidad": "cédula de identidad",
  "tarjeta de identificación": "tarjeta de identificación",
  "solicitar": "solicitar",
  "renovación": "renovación",
  "solictar": "solictar",
  "carne de identidad": "carne de identidad",
  "cedula de identidad": "cedula de identidad",
  "karne de identidad": "karne de identidad",
  "carnet de identidad": "carnet de identidad",
  "sedula de identidad": "sedula de identidad",
  "visitar": "visitar",
  "curoscant": "Curoscant",
  "entrar": "entrar",
  "ingresar": "ingresar",
  "turistear": "turistear",
  "alojarme": "alojarme",
  "planeta": "planeta",
  "hospedarme": "hospedarme",
  "conocer": "conocer",
  "recorrer": "recorrer",
  "explorar": "explorar",
  "territorios inexplorados": "territorios inexplorados",
  "investigar": "investigar",
  "territorios desconocidos": "territorios desconocidos",
  "descubrir": "descubrir",
  "territorios": "territorios",
  "minas": "minas",
  "colonizar": "colonizar",
  "exploración científica": "Exploración científica",
  "buscar": "buscar",
  "exploración minera": "Exploración minera",
  "hacer": "hacer",
  "exploración espacial": "Exploración espacial",
  "dedicarme": "dedicarme",
  "salir a explorar": "salir a explorar",
  "territorio en otro planeta": "territorio en otro planeta",
  "asentar": "asentar",
  "colonia": "colonia",
  "establecer": "establecer",
  "asentamiento": "asentamiento",
  "crear": "crear",
  "comunidad": "comunidad",
  "fundar": "fundar",
  "organizar": "organizar",
  "comunidad planetaria": "comunidad planetaria",
  "obtención": "obtención",
  "recursos naturales": "recursos naturales",
  "extraer": "extraer",
  "recursos": "recursos",
  "minar": "minar",
  "reservas": "reservas",
  "explotar": "explotar",
  "materias primas": "materias primas",
  "producir": "producir",
  "desarrollar": "desarrollar",
  "explotación": "explotación",
  "recolectar": "recolectar",
  "acopio": "acopio",
  "perforación": "perforación",
  "extracción": "extracción",
  "producción": "producción",
  "comerciar": "comerciar",
  "negociar": "negociar",
  "mercaderías": "mercaderías",
  "vender": "vender",
  "empresa": "empresa",
  "exportar": "exportar",
  "productos": "productos",
  "importar": "importar",
  "punto de venta": "punto de venta",
  "tienda": "tienda",
  "emprender": "emprender",
  "negocio": "negocio",
  "comercializar": "comercializar",
  "servicios": "servicios",
  "comercio electrónico": "comercio electrónico",
  "comercio internacional": "comercio internacional",
  "sucursal": "sucursal",
  "comercio interplanetario": "comercio interplanetario",
  "comercio galáctico": "comercio galáctico",
  "comercio intergaláctico": "comercio intergaláctico",
  "servicio militar": "servicio militar",
  "pertenecí": "pertenecí",
  "fuerzas militares": "fuerzas militares",
  "fuerzas armadas": "fuerzas armadas",
  "validar": "validar",
  "confirmar": "confirmar",
  "militar": "militar",
  "fuerza armada": "fuerza armada",
  "fuerza jedi": "fuerza jedi",
  "serví": "serví",
  "combate": "combate",
  "enrolé": "enrolé",
  "alistado": "alistado",
  "milicia": "milicia",
  "enrolado": "enrolado",
  "hice": "hice",
  "orden jedi": "orden jedi",
  "compruebo": "compruebo",
  "participé": "participé",
  "registrar": "registrar",
  "carga": "carga",
  "documentar": "documentar",
  "mercancía": "mercancía",
  "embarque": "embarque",
  "inscribir": "inscribir",
  "inventariar": "inventariar",
  "mercancía comercial": "mercancía comercial",
  "listar": "listar",
  "artículos": "artículos",
  "suminisitros": "suminisitros",
  "gestionar": "gestionar",
  "mercancías comerciales": "mercancías comerciales",
  "productos comerciales": "productos comerciales",
  "bienes comerciales": "bienes comerciales",
  "bienes de consumo": "bienes de consumo",
  "artículos de consumo": "artículos de consumo",
  "acceder": "acceder",
  "beneficios": "beneficios",
  "recibir": "recibir",
  "subsidio": "subsidio",
  "participar": "participar",
  "programa social": "programa social",
  "inscribirme": "inscribirme",
  "sistema de bienestar": "sistema de bienestar",
  "registrarme": "registrarme",
  "ayuda social": "ayuda social",
  "beneficios sociales": "beneficios sociales",
  "beneficio social": "beneficio social",
  "ayuda": "ayuda",
  "invento": "invento",
  "innovación": "innovación",
  "patentar": "patentar",
  "invención": "invención",
  "desarrollo tecnológico": "desarrollo tecnológico",
  "proteger": "proteger",
  "legalizar": "legalizar",
  "formalizar": "formalizar",
  "idea": "idea",
  "avance tecnológico": "avance tecnológico",
  "descubrimiento": "descubrimiento",
  "aparato": "aparato",
  "tecnológico": "tecnológico",
  "dispositivo": "dispositivo",
  "máquina": "máquina",
  "creación tecnológica": "creación tecnológica",
  "creación científica": "creación científica",
  "hallazgo": "hallazgo",
  "avance científico": "avance científico",
  "prototipo": "prototipo",
  "robots": "robots",
  "dróides": "dróides",
  "robot": "robot",
  "droide": "droide",
  "aterrizar": "aterrizar",
  "desembarcar": "desembarcar",
  "desembarque": "desembarque",
  "descender": "descender",
  "descenso": "descenso",
  "llegada al suelo": "llegada al suelo",
  "autorizar": "autorizar",
  "permitir": "permitir",
  "llegada": "llegada",
  "verificar": "verificar",
  "consultar": "consultar",
  "antecedentes penales": "antecedentes penales",
  "revisar": "revisar",
  "historial penal": "historial penal",
  "conducta": "conducta",
  "comportamiento": "comportamiento"
}