{"0": "agradecimiento", "1": "cambio_tema", "2": "consulta_general", "3": "decepcion_ayuda", "4": "despedida", "5": "elige_documento_especifico", "6": "espera_un_poco", "7": "indica_documento_tramitar", "8": "nlu_fallback", "9": "no_mas_ayuda", "10": "no_sabe_tipo_documento", "11": "pregunta_accion_cbs", "12": "pregunta_accion_cdr", "13": "pregunta_accion_cem", "14": "pregunta_accion_cep", "15": "pregunta_accion_cet", "16": "pregunta_accion_cpf", "17": "pregunta_accion_crc", "18": "pregunta_accion_isp", "19": "pregunta_accion_lte", "20": "pregunta_accion_pci", "21": "pregunta_accion_pep", "22": "pregunta_accion_ras", "23": "pregunta_como_estas", "24": "pregunta_contacto_humano", "25": "pregunta_disponibilidad", "26": "pregunta_fecha", "27": "pregunta_funcion_munbot", "28": "pregunta_idiomas", "29": "pregunta_privacidad", "30": "pregunta_que_hora", "31": "pregunta_ubicacion", "32": "preguntar_accion_cat", "33": "preguntar_accion_pat", "34": "preguntar_accion_rdd", "35": "preguntar_accion_riv", "36": "procesar_online", "37": "proporcionar_campo_contacto", "38": "proporcionar_campo_duracion", "39": "proporcionar_campo_horario", "40": "proporcionar_campo_requisito", "41": "proporcionar_campo_sanciones", "42": "proporcionar_campo_telefono", "43": "proporcionar_campo_ubicacion", "44": "reclamo_denuncia", "45": "reclamo_denuncia_3", "46": "reclamo_denuncia_4", "47": "respuesta_bien", "48": "respuesta_mal", "49": "saludo_compuesto", "50": "saludo_simple", "51": "select_opcion_dia_cita", "52": "select_opcion_hora_cita", "53": "si_mas_ayuda", "54": "solicitar_cita", "55": "solicitar_info_cita_2", "56": "solicitar_info_cita_3", "57": "solicitar_info_cita_4", "58": "solicitar_info_reclamo_2", "59": "solicitud_documento_general", "60": "sugerir_cita_afirmativa", "61": "sugerir_cita_negativa", "62": "user_confirma_cita"}